pydrever/__init__.py
pydrever/calculation/__init__.py
pydrever/calculation/_hydrodynamicsinterpolation.py
pydrever/calculation/_dikernel/__init__.py
pydrever/calculation/_dikernel/_dikernel.py
pydrever/calculation/_dikernel/_dikernelcreferences.py
pydrever/calculation/_dikernel/_dikernelinputparser.py
pydrever/calculation/_dikernel/_dikerneloutputparser.py
pydrever/calculation/_dikernel/_inputservices.py
pydrever/calculation/_dikernel/_dikerneldll/DiKErnel.Core.dll
pydrever/calculation/_dikernel/_dikerneldll/DiKErnel.DomainLibrary.dll
pydrever/calculation/_dikernel/_dikerneldll/DiKErnel.External.Overtopping.dll
pydrever/calculation/_dikernel/_dikerneldll/DiKErnel.FunctionLibrary.dll
pydrever/calculation/_dikernel/_dikerneldll/DiKErnel.Integration.dll
pydrever/calculation/_dikernel/_dikerneldll/DiKErnel.Util.dll
pydrever/calculation/_dikernel/_dikerneldll/dllDikesOvertopping.dll
pydrever/calculation/_dikernel/_dikerneldll/feedbackDLL.dll
pydrever/calculation/_dikernel/_dikerneldll/libifcoremd.dll
pydrever/calculation/_dikernel/_dikerneldll/libiomp5md.dll
pydrever/calculation/_dikernel/_dikerneldll/libmmd.dll
pydrever/data/__init__.py
pydrever/data/_calculationmethods.py
pydrever/data/_dikernelcalculationsettings.py
pydrever/data/_dikernelinput.py
pydrever/data/_dikerneloutput.py
pydrever/data/_dikerneloutputspecification.py
pydrever/data/_dikernelrevetmentzonespecification.py
pydrever/data/_dikeschematization.py
pydrever/data/_quantities.py
pydrever/data/_toplayertypes.py
pydrever/io/__init__.py
pydrever/io/_prflreader.py
pydrever/visualization/__init__.py
pydrever/visualization/_visualization_animated.py
pydrever/visualization/_visualization_damage.py
pydrever-0.9.0.dist-info/LICENSE
pydrever-0.9.0.dist-info/METADATA
pydrever-0.9.0.dist-info/WHEEL
pydrever-0.9.0.dist-info/top_level.txt
pydrever-0.9.0.dist-info/RECORD
