Metadata-Version: 2.1
Name: pydrever
Version: 0.9.0
Summary: Tools that facilitate analysis of dike safety against flooding.
Author-email: Pieter van Geer <pieter.vangeer@deltares.com>
License: GNU LESSER GENERAL PUBLIC LICENSE
Project-URL: Homepage, https://github.com/Deltares-research/dike-revetment-erosion-pytools.git
Project-URL: Issues, https://github.com/Deltares-research/dike-revetment-erosion-pytools/issues
Classifier: Programming Language :: Python :: 3.10
Classifier: License :: OSI Approved :: GNU Lesser General Public License v3 or later (LGPLv3+)
Classifier: Operating System :: Microsoft :: Windows
Requires-Python: >=3.10
License-File: LICENSE
Requires-Dist: numpy
Requires-Dist: matplotlib
Requires-Dist: pythonnet
